LICENSE
MANIFEST.in
README.rst
pytest_contextfixture.py
setup.py
pytest_contextfixture.egg-info/PKG-INFO
pytest_contextfixture.egg-info/SOURCES.txt
pytest_contextfixture.egg-info/dependency_links.txt
pytest_contextfixture.egg-info/entry_points.txt
pytest_contextfixture.egg-info/requires.txt
pytest_contextfixture.egg-info/top_level.txt