Metadata-Version: 1.0
Name: pytest-contextfixture
Version: 0.1.1
Summary: Define pytest fixtures as context managers.
Home-page: http://github.com/pelme/pytest-contextfixture/
Author: Andreas Pelme
Author-email: andreas@pelme.se
License: UNKNOWN
Platform: UNKNOWN
Classifier: Development Status :: 4 - Beta
Classifier: Intended Audience :: Developers
Classifier: License :: OSI Approved :: BSD License
Classifier: Operating System :: OS Independent
Classifier: Programming Language :: Python
Classifier: Topic :: Software Development :: Testing
